LICENSE.md
MANIFEST.in
README.md
RELEASE.md
requirements.txt
setup.cfg
setup.py
ondewo_nlu_webhook_server/__init__.c
ondewo_nlu_webhook_server/__init__.py
ondewo_nlu_webhook_server/constants.c
ondewo_nlu_webhook_server/constants.py
ondewo_nlu_webhook_server/custom_exceptions.c
ondewo_nlu_webhook_server/custom_exceptions.py
ondewo_nlu_webhook_server/globals.c
ondewo_nlu_webhook_server/globals.py
ondewo_nlu_webhook_server/language_code.c
ondewo_nlu_webhook_server/language_code.py
ondewo_nlu_webhook_server/version.c
ondewo_nlu_webhook_server/version.py
ondewo_nlu_webhook_server.egg-info/PKG-INFO
ondewo_nlu_webhook_server.egg-info/SOURCES.txt
ondewo_nlu_webhook_server.egg-info/dependency_links.txt
ondewo_nlu_webhook_server.egg-info/requires.txt
ondewo_nlu_webhook_server.egg-info/top_level.txt
ondewo_nlu_webhook_server/resources/__init__.c
ondewo_nlu_webhook_server/resources/__init__.py
ondewo_nlu_webhook_server/server/__init__.c
ondewo_nlu_webhook_server/server/__init__.py
ondewo_nlu_webhook_server/server/__main__.c
ondewo_nlu_webhook_server/server/__main__.py
ondewo_nlu_webhook_server/server/base_models.c
ondewo_nlu_webhook_server/server/base_models.py
ondewo_nlu_webhook_server/server/relay.c
ondewo_nlu_webhook_server/server/relay.py
ondewo_nlu_webhook_server/server/server.c
ondewo_nlu_webhook_server/server/server.py
ondewo_nlu_webhook_server_custom_integration/__init__.c
ondewo_nlu_webhook_server_custom_integration/__init__.py
ondewo_nlu_webhook_server_custom_integration/auth.c
ondewo_nlu_webhook_server_custom_integration/auth.py
ondewo_nlu_webhook_server_custom_integration/custom_integration.c
ondewo_nlu_webhook_server_custom_integration/custom_integration.py
ondewo_nlu_webhook_server_custom_integration/error_handlers.c
ondewo_nlu_webhook_server_custom_integration/error_handlers.py
ondewo_nlu_webhook_server_custom_integration/http_services.c
ondewo_nlu_webhook_server_custom_integration/http_services.py
ondewo_nlu_webhook_server_custom_integration/utils/__init__.c
ondewo_nlu_webhook_server_custom_integration/utils/__init__.py
ondewo_nlu_webhook_server_custom_integration/utils/helpers.c
ondewo_nlu_webhook_server_custom_integration/utils/helpers.py