Metadata-Version: 2.1
Name: ondewo-nlu-webhook-server
Version: 2.0.0
Summary: ONDEWO NLU Webhook Server Python
Home-page: https://github.com/ondewo/ondewo-nlu-webhook-server-python
Author: Ondewo GmbH
Author-email: office@ondewo.com
Classifier: Development Status :: 5 - Production/Stable
Classifier: Intended Audience :: Developers
Classifier: Topic :: Software Development :: Libraries
Classifier: License :: OSI Approved :: Apache Software License
Classifier: Programming Language :: Python :: 3.10
Classifier: Programming Language :: Python :: 3.11
Classifier: Programming Language :: Python :: 3.12
Classifier: Programming Language :: Python :: 3.13
Classifier: Operating System :: OS Independent
Requires-Python: >=3.10
License-File: LICENSE.md
Requires-Dist: ondewo-nlu-client>=6.0.0
Requires-Dist: beautifulsoup4>=4.12.3
Requires-Dist: cython
Requires-Dist: dataclasses>=0.6
Requires-Dist: dataclasses-json>=0.5.4
Requires-Dist: docker>=7.1.0
Requires-Dist: fastapi>=0.115.6
Requires-Dist: httpx>=0.27.2
Requires-Dist: jsonschema>=4.23.0
Requires-Dist: langcodes>=3.4.1
Requires-Dist: numpy>=2.1.1
Requires-Dist: ondewo-logging>=3.3.3
Requires-Dist: pip-licenses
Requires-Dist: py~=1.11.0
Requires-Dist: pydantic>=2.8.2
Requires-Dist: python-dateutil>=2.9.0.post0
Requires-Dist: python-dotenv>=1.0.1
Requires-Dist: pytz>=2023.2
Requires-Dist: regex>=2024.4.16
Requires-Dist: requests>=2.32.2
Requires-Dist: semantic-version>=2.10.0
Requires-Dist: setuptools>=67.1.0
Requires-Dist: starlette>=0.40.0
Requires-Dist: typing_extensions>=4.12.2
Requires-Dist: uvicorn>=0.30.4
